HISTORY.rst
MANIFEST.in
README.rst
requirements.txt
setup.py
zapi/__init__.py
zapi.egg-info/PKG-INFO
zapi.egg-info/SOURCES.txt
zapi.egg-info/dependency_links.txt
zapi.egg-info/requires.txt
zapi.egg-info/top_level.txt
zapi/core/__init__.py
zapi/core/app.py
zapi/core/common.py
zapi/core/config.py
zapi/core/db.py
zapi/core/exceptions.py
zapi/core/input.py
zapi/core/load.py
zapi/core/logger.py
zapi/core/model.py
zapi/core/route.py
zapi/core/utils.py