Metadata-Version: 1.0
Name: zapi
Version: 0.0.8
Summary: An easy lightweight web framework by python.
Home-page: https://github.com/linzhonghong/zapi
Author: Zhonghong Lin
Author-email: 1529909253@qq.com
License: MIT
Download-URL: https://github.com/linzhonghong/zapi/tarball/2016-05-10
Platform: Windows
Platform: Unix
Classifier: Development Status :: 4 - Beta
Classifier: Intended Audience :: Developers
Classifier: License :: OSI Approved :: MIT License
Classifier: Natural Language :: English
Classifier: Operating System :: Microsoft :: Windows
Classifier: Operating System :: Unix
Classifier: Programming Language :: Python
Classifier: Programming Language :: Python :: 2
Classifier: Programming Language :: Python :: 2.7
Classifier: Programming Language :: Python :: 2 :: Only
